radio_sdk.py
radio_sdk-0.1.0.dist-info/License.txt
radio_sdk-0.1.0.dist-info/METADATA
radio_sdk-0.1.0.dist-info/WHEEL
radio_sdk-0.1.0.dist-info/top_level.txt
radio_sdk-0.1.0.dist-info/RECORD
