Metadata-Version: 2.1
Name: radio-sdk
Version: 0.1.0
Summary: A Python SDK for the Radio Browser API
Home-page: https://github.com/brendanjamesmulhern/radio_sdk
Author: Brendan Mulhern
Author-email: UNKNOWN
License: UNKNOWN
Platform: UNKNOWN
Classifier: Development Status :: 3 - Alpha
Classifier: Intended Audience :: Developers
Classifier: License :: OSI Approved :: MIT License
Classifier: Programming Language :: Python :: 3
Classifier: Programming Language :: Python :: 3.4
